plaintext_playlist_py/__init__.py
plaintext_playlist_py/__main__.py
plaintext_playlist_py/funcs.py
plaintext_playlist_py/id3.py
plaintext_playlist_py/py.typed
plaintext_playlist_py/ui.py
plaintext_playlist_py-0.1.0.dist-info/licenses/LICENSE
plaintext_playlist_py-0.1.0.dist-info/METADATA
plaintext_playlist_py-0.1.0.dist-info/WHEEL
plaintext_playlist_py-0.1.0.dist-info/entry_points.txt
plaintext_playlist_py-0.1.0.dist-info/top_level.txt
plaintext_playlist_py-0.1.0.dist-info/RECORD
