Metadata-Version: 2.4
Name: plaintext_playlist_py
Version: 0.1.0
Summary: Parse plaintext playlists into python data
Author: purarue
License-Expression: MIT
Project-URL: Homepage, https://github.com/purarue/plaintext_playlist_py
Keywords: music
Classifier: Programming Language :: Python
Classifier: Programming Language :: Python :: 3
Classifier: Programming Language :: Python :: 3 :: Only
Classifier: Programming Language :: Python :: 3.10
Classifier: Programming Language :: Python :: 3.11
Classifier: Programming Language :: Python :: 3.12
Classifier: Programming Language :: Python :: 3.13
Classifier: Programming Language :: Python :: 3.14
Requires-Python: >=3.10
License-File: LICENSE
Requires-Dist: Pillow
Requires-Dist: click>=8.0
Requires-Dist: more-itertools
Requires-Dist: mutagen
Requires-Dist: requests
Provides-Extra: testing
Requires-Dist: flake8; extra == "testing"
Requires-Dist: mypy; extra == "testing"
Dynamic: license-file
